pyavrocd/__init__.py
pyavrocd/breakexec.py
pyavrocd/deviceinfo/__init__.py
pyavrocd/deviceinfo/collect.py
pyavrocd/deviceinfo/devices/alldevices.py
pyavrocd/deviceinfo/devices/at90can128.py
pyavrocd/deviceinfo/devices/at90can32.py
pyavrocd/deviceinfo/devices/at90can64.py
pyavrocd/deviceinfo/devices/at90pwm1.py
pyavrocd/deviceinfo/devices/at90pwm161.py
pyavrocd/deviceinfo/devices/at90pwm216.py
pyavrocd/deviceinfo/devices/at90pwm2b.py
pyavrocd/deviceinfo/devices/at90pwm3.py
pyavrocd/deviceinfo/devices/at90pwm316.py
pyavrocd/deviceinfo/devices/at90pwm3b.py
pyavrocd/deviceinfo/devices/at90pwm81.py
pyavrocd/deviceinfo/devices/at90usb1286.py
pyavrocd/deviceinfo/devices/at90usb1287.py
pyavrocd/deviceinfo/devices/at90usb162.py
pyavrocd/deviceinfo/devices/at90usb646.py
pyavrocd/deviceinfo/devices/at90usb647.py
pyavrocd/deviceinfo/devices/at90usb82.py
pyavrocd/deviceinfo/devices/atmega128.py
pyavrocd/deviceinfo/devices/atmega1280.py
pyavrocd/deviceinfo/devices/atmega1281.py
pyavrocd/deviceinfo/devices/atmega1284.py
pyavrocd/deviceinfo/devices/atmega1284p.py
pyavrocd/deviceinfo/devices/atmega1284rfr2.py
pyavrocd/deviceinfo/devices/atmega128a.py
pyavrocd/deviceinfo/devices/atmega128rfa1.py
pyavrocd/deviceinfo/devices/atmega128rfr2.py
pyavrocd/deviceinfo/devices/atmega16.py
pyavrocd/deviceinfo/devices/atmega162.py
pyavrocd/deviceinfo/devices/atmega164a.py
pyavrocd/deviceinfo/devices/atmega164p.py
pyavrocd/deviceinfo/devices/atmega164pa.py
pyavrocd/deviceinfo/devices/atmega165a.py
pyavrocd/deviceinfo/devices/atmega165p.py
pyavrocd/deviceinfo/devices/atmega165pa.py
pyavrocd/deviceinfo/devices/atmega168.py
pyavrocd/deviceinfo/devices/atmega168a.py
pyavrocd/deviceinfo/devices/atmega168p.py
pyavrocd/deviceinfo/devices/atmega168pa.py
pyavrocd/deviceinfo/devices/atmega168pb.py
pyavrocd/deviceinfo/devices/atmega169a.py
pyavrocd/deviceinfo/devices/atmega169p.py
pyavrocd/deviceinfo/devices/atmega169pa.py
pyavrocd/deviceinfo/devices/atmega16a.py
pyavrocd/deviceinfo/devices/atmega16hva.py
pyavrocd-1.0.0.dist-info/METADATA
pyavrocd-1.0.0.dist-info/WHEEL
pyavrocd-1.0.0.dist-info/entry_points.txt
pyavrocd-1.0.0.dist-info/licenses/LICENSE
pyavrocd-1.0.0.dist-info/RECORD
