Metadata-Version: 2.4
Name: pyavrocd
Version: 1.0.0
Summary: A cross-platform GDB server for AVR MCUs
License-File: LICENSE
Keywords: AVR,EDBG,gdb-server,debugging
Author: Bernhard Nebel
Author-email: nebel@arduino-craft-corner.de
Requires-Python: <3.15,>=3.10
Classifier: Programming Language :: Python :: 3
Classifier: Programming Language :: Python :: 3.10
Classifier: Programming Language :: Python :: 3.11
Classifier: Programming Language :: Python :: 3.12
Classifier: Programming Language :: Python :: 3.13
Classifier: Programming Language :: Python :: 3.14
Classifier: Operating System :: MacOS
Classifier: Operating System :: Microsoft :: Windows
Classifier: Operating System :: POSIX :: Linux
Classifier: Development Status :: 4 - Beta
Classifier: Environment :: Console
Classifier: Intended Audience :: Developers
Classifier: License :: OSI Approved :: MIT License
Classifier: Topic :: Software Development :: Debuggers
Requires-Dist: markdown-include (>=0.8.1,<0.9.0)
Requires-Dist: mkdocs (>=1.6.1,<2.0.0)
Requires-Dist: pexpect (>=4.9.0,<5.0.0)
Requires-Dist: pre-commit (>=4.2.0,<5.0.0)
Requires-Dist: pyedbglib (>=2.24.2.18,<3.0.0.0)
Requires-Dist: pyinstaller (>=6.12.0,<7.0.0)
Requires-Dist: pylint (>=4.0.0,<5.0.0)
Requires-Dist: pymcuprog (>=3.17.3.45,<4.0.0.0)
Requires-Dist: pytest (>=8.4.2,<9.0.0)
Requires-Dist: pytest-cov (>=7.0.0,<8.0.0)
Requires-Dist: pyusb (>=1.3.1,<1.4.0)
Project-URL: Bug Tracker, https://github.com/felias-fogg/PyAvrOCD/issues
Project-URL: Documentation, https://pyavrocd.io
Project-URL: Repository, https://github.com/felias-fogg/PyAvrOCD
